[{"deg360":2.7,"lon":-121.3,"deg60":2.4,"deg90":2.4,"deg45":2.3,"deg0":0.9,"deg30":2,"lat":51.65},{"deg360":2.7,"lon":-121.35,"deg60":2.4,"deg90":2.4,"deg45":2.3,"deg0":0.9,"deg30":2,"lat":51.75},{"deg360":2.6,"lon":-121.4,"deg60":2.4,"deg90":2.3,"deg45":2.3,"deg0":0.9,"deg30":2,"lat":51.3},{"deg360":2.1,"lon":-122.28,"deg60":1.9,"deg90":1.8,"deg45":1.8,"deg0":0.9,"deg30":1.6,"lat":49.05},{"deg360":2.4,"lon":-119.69,"deg60":2.1,"deg90":2.1,"deg45":2,"deg0":1,"deg30":1.8,"lat":50.96},{"deg360":2.1,"lon":-122.47,"deg60":1.9,"deg90":1.8,"deg45":1.8,"deg0":0.9,"deg30":1.6,"lat":49.06},{"deg360":1.9,"lon":-126.92,"deg60":1.7,"deg90":1.6,"deg45":1.6,"deg0":0.7,"deg30":1.5,"lat":50.58},{"deg360":2.6,"lon":-122.45,"deg60":2.3,"deg90":2.3,"deg45":2.2,"deg0":0.8,"deg30":1.9,"lat":52.64},{"deg360":2.5,"lon":-123.28,"deg60":2.3,"deg90":2.2,"deg45":2.1,"deg0":0.9,"deg30":1.9,"lat":52.08},{"deg360":2.7,"lon":-122.23,"deg60":2.4,"deg90":2.4,"deg45":2.3,"deg0":0.9,"deg30":2,"lat":51.79},{"deg360":2.2,"lon":-125.32,"deg60":2,"deg90":1.9,"deg45":1.9,"deg0":0.8,"deg30":1.7,"lat":52.47},{"deg360":2.3,"lon":-119.17,"deg60":2.1,"deg90":2,"deg45":2,"deg0":1,"deg30":1.8,"lat":50.97},{"deg360":2.6,"lon":-116.92,"deg60":2.3,"deg90":2.2,"deg45":2.2,"deg0":1.1,"deg30":1.9,"lat":50.17},{"deg360":2.2,"lon":-119.19,"deg60":2,"deg90":1.9,"deg45":1.9,"deg0":1,"deg30":1.7,"lat":50.45},{"deg360":2.6,"lon":-121.28,"deg60":2.3,"deg90":2.3,"deg45":2.2,"deg0":1,"deg30":2,"lat":50.73},{"deg360":2.2,"lon":-120.63,"deg60":2,"deg90":1.9,"deg45":1.9,"deg0":1,"deg30":1.7,"lat":49.93},{"deg360":1.4,"lon":-133.69,"deg60":1.3,"deg90":1.3,"deg45":1.3,"deg0":0.4,"deg30":1.1,"lat":59.58},{"deg360":2.5,"lon":-122.45,"deg60":2.3,"deg90":2.3,"deg45":2.2,"deg0":0.8,"deg30":1.9,"lat":52.72},{"deg360":2.5,"lon":-119.32,"deg60":2.3,"deg90":2.2,"deg45":2.1,"deg0":0.9,"deg30":1.9,"lat":51.79},{"deg360":2.5,"lon":-116.97,"deg60":2.3,"deg90":2.2,"deg45":2.1,"deg0":1.1,"deg30":1.9,"lat":49.63},{"deg360":2.1,"lon":-125.15,"deg60":1.9,"deg90":1.8,"deg45":1.8,"deg0":0.8,"deg30":1.6,"lat":48.83},{"deg360":2.5,"lon":-120.13,"deg60":2.3,"deg90":2.2,"deg45":2.1,"deg0":1,"deg30":1.9,"lat":51.18},{"deg360":3.3,"lon":-115.22,"deg60":3,"deg90":2.9,"deg45":2.8,"deg0":1.2,"deg30":2.5,"lat":49.23},{"deg360":2.4,"lon":-122.68,"deg60":2.1,"deg90":2.1,"deg45":2,"deg0":0.7,"deg30":1.8,"lat":54.49},{"deg360":2.1,"lon":-119.08,"deg60":1.9,"deg90":1.8,"deg45":1.8,"deg0":1.1,"deg30":1.6,"lat":49.44},{"deg360":1.8,"lon":-126.75,"deg60":1.7,"deg90":1.6,"deg45":1.6,"deg0":0.6,"deg30":1.4,"lat":52.36},{"deg360":2,"lon":-125.14,"deg60":1.8,"deg90":1.7,"deg45":1.7,"deg0":0.8,"deg30":1.5,"lat":50.4},{"deg360":2.5,"lon":-119.92,"deg60":2.3,"deg90":2.3,"deg45":2.2,"deg0":0.9,"deg30":1.9,"lat":51.6},{"deg360":2.3,"lon":-122.62,"deg60":2.1,"deg90":2,"deg45":2,"deg0":0.9,"deg30":1.7,"lat":50.48},{"deg360":2.3,"lon":-119.38,"deg60":2.1,"deg90":2,"deg45":2,"deg0":1,"deg30":1.8,"lat":50.88},{"deg360":2.5,"lon":-119.31,"deg60":2.3,"deg90":2.2,"deg45":2.1,"deg0":0.9,"deg30":1.9,"lat":52.11},{"deg360":2.3,"lon":-117.67,"deg60":2.1,"deg90":2,"deg45":2,"deg0":1.1,"deg30":1.8,"lat":49.25},{"deg360":2.2,"lon":-121.44,"deg60":1.9,"deg90":1.9,"deg45":1.9,"deg0":0.9,"deg30":1.7,"lat":49.86},{"deg360":2,"lon":-123.42,"deg60":1.8,"deg90":1.7,"deg45":1.7,"deg0":0.9,"deg30":1.6,"lat":49.36},{"deg360":2,"lon":-123.15,"deg60":1.8,"deg90":1.7,"deg45":1.7,"deg0":0.8,"deg30":1.5,"lat":49.77},{"deg360":3,"lon":-116.27,"deg60":2.6,"deg90":2.6,"deg45":2.5,"deg0":1.1,"deg30":2.2,"lat":50.83},{"deg360":2,"lon":-123.2,"deg60":1.8,"deg90":1.7,"deg45":1.7,"deg0":0.8,"deg30":1.5,"lat":49.63},{"deg360":2.9,"lon":-121.28,"deg60":2.6,"deg90":2.6,"deg45":2.5,"deg0":0.6,"deg30":2.2,"lat":56.76},{"deg360":2.1,"lon":-123.02,"deg60":1.8,"deg90":1.7,"deg45":1.8,"deg0":0.9,"deg30":1.6,"lat":49.26},{"deg360":2.2,"lon":-125.76,"deg60":2,"deg90":2,"deg45":1.9,"deg0":0.7,"deg30":1.7,"lat":54.23},{"deg360":2.3,"lon":-117.87,"deg60":2,"deg90":2,"deg45":2,"deg0":1.1,"deg30":1.7,"lat":49.98},{"deg360":2.6,"lon":-121.33,"deg60":2.3,"deg90":2.3,"deg45":2.2,"deg0":1,"deg30":2,"lat":50.81},{"deg360":2,"lon":-125.28,"deg60":1.8,"deg90":1.7,"deg45":1.7,"deg0":0.8,"deg30":1.5,"lat":50.03},{"deg360":3.1,"lon":-115.81,"deg60":2.8,"deg90":2.7,"deg45":2.6,"deg0":1.2,"deg30":2.3,"lat":50.15},{"deg360":2.3,"lon":-117.66,"deg60":2.1,"deg90":2,"deg45":2,"deg0":1.1,"deg30":1.8,"lat":49.29},{"deg360":2.1,"lon":-119.76,"deg60":1.9,"deg90":1.8,"deg45":1.8,"deg0":1.1,"deg30":1.6,"lat":49.19},{"deg360":2.1,"lon":-123.88,"deg60":1.9,"deg90":1.8,"deg45":1.8,"deg0":0.9,"deg30":1.6,"lat":49.12},{"deg360":2.2,"lon":-123.4,"deg60":1.9,"deg90":1.8,"deg45":1.8,"deg0":0.9,"deg30":1.6,"lat":48.57},{"deg360":2.9,"lon":-120.96,"deg60":2.7,"deg90":2.7,"deg45":2.5,"deg0":0.7,"deg30":2.2,"lat":56.28},{"deg360":2.3,"lon":-119.68,"deg60":2.1,"deg90":2.1,"deg45":2,"deg0":1,"deg30":1.8,"lat":50.82},{"deg360":2.1,"lon":-123.72,"deg60":1.9,"deg90":1.8,"deg45":1.8,"deg0":0.9,"deg30":1.6,"lat":48.92},{"deg360":2.2,"lon":-118.62,"deg60":2,"deg90":1.9,"deg45":1.9,"deg0":1.1,"deg30":1.7,"lat":50.24},{"deg360":2.8,"lon":-121.63,"deg60":2.6,"deg90":2.5,"deg45":2.4,"deg0":0.7,"deg30":2.1,"lat":55.7},{"deg360":2.1,"lon":-121.95,"deg60":1.9,"deg90":1.8,"deg45":1.8,"deg0":0.9,"deg30":1.6,"lat":49.17},{"deg360":2.1,"lon":-118.82,"deg60":1.9,"deg90":1.8,"deg45":1.8,"deg0":1.1,"deg30":1.6,"lat":49.55},{"deg360":2.2,"lon":-118.2,"deg60":2,"deg90":1.9,"deg45":1.9,"deg0":1.2,"deg30":1.7,"lat":49.05},{"deg360":2.6,"lon":-120.03,"deg60":2.3,"deg90":2.3,"deg45":2.2,"deg0":0.9,"deg30":2,"lat":51.65},{"deg360":2.6,"lon":-121.59,"deg60":2.4,"deg90":2.3,"deg45":2.2,"deg0":0.9,"deg30":2,"lat":51.09},{"deg360":1.8,"lon":-127.58,"deg60":1.6,"deg90":1.5,"deg45":1.6,"deg0":0.7,"deg30":1.4,"lat":50.6},{"deg360":2.1,"lon":-123.59,"deg60":1.9,"deg90":1.8,"deg45":1.8,"deg0":0.9,"deg30":1.6,"lat":48.7},{"deg360":2.2,"lon":-119.25,"deg60":2,"deg90":1.9,"deg45":1.9,"deg0":1.1,"deg30":1.7,"lat":50.23},{"deg360":2.3,"lon":-120.8,"deg60":2.1,"deg90":2,"deg45":2,"deg0":1,"deg30":1.8,"lat":50.1},{"deg360":2,"lon":-124.94,"deg60":1.8,"deg90":1.7,"deg45":1.7,"deg0":0.8,"deg30":1.5,"lat":49.68},{"deg360":2.6,"lon":-116.96,"deg60":2.3,"deg90":2.2,"deg45":2.2,"deg0":1.1,"deg30":1.9,"lat":50.2},{"deg360":2,"lon":-122.76,"deg60":1.8,"deg90":1.7,"deg45":1.8,"deg0":0.9,"deg30":1.6,"lat":49.26},{"deg360":2,"lon":-124.99,"deg60":1.8,"deg90":1.7,"deg45":1.7,"deg0":0.8,"deg30":1.5,"lat":49.68},{"deg360":2.1,"lon":-123.62,"deg60":1.9,"deg90":1.8,"deg45":1.8,"deg0":0.9,"deg30":1.6,"lat":48.74},{"deg360":3.1,"lon":-115.76,"deg60":2.8,"deg90":2.7,"deg45":2.6,"deg0":1.2,"deg30":2.3,"lat":49.52},{"deg360":2.6,"lon":-116.82,"deg60":2.3,"deg90":2.3,"deg45":2.2,"deg0":1.1,"deg30":2,"lat":49.68},{"deg360":2.7,"lon":-116.5,"deg60":2.4,"deg90":2.4,"deg45":2.3,"deg0":1.2,"deg30":2,"lat":49.1},{"deg360":2.1,"lon":-121.96,"deg60":1.9,"deg90":1.8,"deg45":1.8,"deg0":0.9,"deg30":1.6,"lat":49.07},{"deg360":2,"lon":-125.04,"deg60":1.8,"deg90":1.7,"deg45":1.7,"deg0":0.8,"deg30":1.5,"lat":49.66},{"deg360":3,"lon":-120.22,"deg60":2.8,"deg90":2.8,"deg45":2.6,"deg0":0.7,"deg30":2.3,"lat":55.76},{"deg360":1.7,"lon":-130.01,"deg60":1.6,"deg90":1.6,"deg45":1.5,"deg0":0.5,"deg30":1.3,"lat":58.46},{"deg360":2.2,"lon":-125.83,"deg60":2,"deg90":2,"deg45":1.9,"deg0":0.7,"deg30":1.7,"lat":54.3},{"deg360":2.3,"lon":-118.05,"deg60":2,"deg90":2,"deg45":1.9,"deg0":1.1,"deg30":1.7,"lat":49.42},{"deg360":2.1,"lon":-122.99,"deg60":1.9,"deg90":1.8,"deg45":1.8,"deg0":0.9,"deg30":1.6,"lat":49.12},{"deg360":2,"lon":-124.81,"deg60":1.8,"deg90":1.7,"deg45":1.7,"deg0":0.8,"deg30":1.5,"lat":49.54},{"deg360":2,"lon":-121.43,"deg60":1.8,"deg90":1.7,"deg45":1.7,"deg0":0.9,"deg30":1.5,"lat":49.48},{"deg360":2.7,"lon":-117.18,"deg60":2.4,"deg90":2.3,"deg45":2.2,"deg0":1,"deg30":2,"lat":51.49},{"deg360":2.3,"lon":-120.21,"deg60":2.1,"deg90":2,"deg45":2,"deg0":1,"deg30":1.8,"lat":50.17},{"deg360":2.1,"lon":-123.7,"deg60":1.9,"deg90":1.8,"deg45":1.8,"deg0":0.9,"deg30":1.6,"lat":48.78},{"deg360":3,"lon":-116.13,"deg60":2.7,"deg90":2.6,"deg45":2.5,"deg0":1.1,"deg30":2.2,"lat":50.71},{"deg360":2.2,"lon":-118.13,"deg60":2,"deg90":1.9,"deg45":1.9,"deg0":1.1,"deg30":1.7,"lat":49.78},{"deg360":3.5,"lon":-114.92,"deg60":3.1,"deg90":3,"deg45":2.9,"deg0":1.2,"deg30":2.5,"lat":50.01},{"deg360":3.3,"lon":-115.11,"deg60":3,"deg90":2.9,"deg45":2.8,"deg0":1.2,"deg30":2.4,"lat":49.31},{"deg360":2.3,"lon":-119.14,"deg60":2,"deg90":2,"deg45":1.9,"deg0":1,"deg30":1.7,"lat":50.54},{"deg360":2.1,"lon":-124.37,"deg60":1.8,"deg90":1.7,"deg45":1.8,"deg0":0.9,"deg30":1.6,"lat":49.28},{"deg360":2.2,"lon":-123.41,"deg60":1.9,"deg90":1.8,"deg45":1.8,"deg0":0.9,"deg30":1.7,"lat":48.44},{"deg360":3.1,"lon":-115.86,"deg60":2.8,"deg90":2.7,"deg45":2.6,"deg0":1.2,"deg30":2.3,"lat":50.34},{"deg360":2.3,"lon":-119.55,"deg60":2,"deg90":2,"deg45":1.9,"deg0":1,"deg30":1.7,"lat":50.5},{"deg360":2.1,"lon":-124.35,"deg60":1.9,"deg90":1.8,"deg45":1.8,"deg0":0.9,"deg30":1.6,"lat":49.49},{"deg360":2,"lon":-124.81,"deg60":1.8,"deg90":1.7,"deg45":1.7,"deg0":0.8,"deg30":1.5,"lat":49.49},{"deg360":2.3,"lon":-118.07,"deg60":2,"deg90":1.9,"deg45":1.9,"deg0":1.1,"deg30":1.7,"lat":49.87},{"deg360":2.4,"lon":-122.48,"deg60":2.2,"deg90":2.1,"deg45":2,"deg0":0.7,"deg30":1.8,"lat":53.98},{"deg360":3.3,"lon":-115.07,"deg60":2.9,"deg90":2.9,"deg45":2.8,"deg0":1.2,"deg30":2.4,"lat":49.5},{"deg360":2.9,"lon":-116.5,"deg60":2.6,"deg90":2.5,"deg45":2.4,"deg0":1.1,"deg30":2.1,"lat":51.39},{"deg360":2.6,"lon":-121.1,"deg60":2.4,"deg90":2.4,"deg45":2.3,"deg0":0.9,"deg30":2,"lat":51.77},{"deg360":2.2,"lon":-126.63,"deg60":2,"deg90":2,"deg45":1.9,"deg0":0.6,"deg30":1.7,"lat":55.32},{"deg360":2.3,"lon":-124.55,"deg60":2,"deg90":2,"deg45":1.9,"deg0":0.7,"deg30":1.7,"lat":54.06},{"deg360":2.1,"lon":-122.58,"deg60":1.9,"deg90":1.8,"deg45":1.8,"deg0":0.9,"deg30":1.6,"lat":49.16},{"deg360":2.3,"lon":-122.7,"deg60":2.1,"deg90":2.1,"deg45":2,"deg0":0.5,"deg30":1.8,"lat":58.81},{"deg360":2.3,"lon":-124.25,"deg60":2.1,"deg90":2,"deg45":1.9,"deg0":0.7,"deg30":1.7,"lat":54.44},{"deg360":3,"lon":-120.85,"deg60":2.7,"deg90":2.7,"deg45":2.6,"deg0":0.7,"deg30":2.2,"lat":56.25},{"deg360":2.2,"lon":-124.85,"deg60":2,"deg90":2,"deg45":1.9,"deg0":0.7,"deg30":1.7,"lat":54.06},{"deg360":2.3,"lon":-117.56,"deg60":2.1,"deg90":2,"deg45":2,"deg0":1.1,"deg30":1.8,"lat":49.1},{"deg360":2.1,"lon":-123.46,"deg60":1.9,"deg90":1.8,"deg45":1.8,"deg0":0.9,"deg30":1.6,"lat":48.77},{"deg360":2.1,"lon":-123.5,"deg60":1.9,"deg90":1.8,"deg45":1.8,"deg0":0.9,"deg30":1.6,"lat":48.85},{"deg360":2,"lon":-124.06,"deg60":1.8,"deg90":1.7,"deg45":1.7,"deg0":0.8,"deg30":1.5,"lat":49.65},{"deg360":2.3,"lon":-117.7,"deg60":2.1,"deg90":2,"deg45":2,"deg0":1.1,"deg30":1.8,"lat":49.21},{"deg360":2.3,"lon":-124.7,"deg60":2.1,"deg90":2,"deg45":1.9,"deg0":0.6,"deg30":1.7,"lat":55.78},{"deg360":2,"lon":-123.51,"deg60":1.8,"deg90":1.7,"deg45":1.7,"deg0":0.8,"deg30":1.5,"lat":49.4},{"deg360":2.1,"lon":-124.48,"deg60":1.8,"deg90":1.7,"deg45":1.8,"deg0":0.8,"deg30":1.6,"lat":49.68},{"deg360":1.7,"lon":-129.95,"deg60":1.5,"deg90":1.5,"deg45":1.5,"deg0":0.5,"deg30":1.3,"lat":54.99},{"deg360":1.8,"lon":-129.22,"deg60":1.6,"deg90":1.6,"deg45":1.6,"deg0":0.5,"deg30":1.4,"lat":55.19},{"deg360":2,"lon":-126.08,"deg60":1.8,"deg90":1.7,"deg45":1.7,"deg0":0.8,"deg30":1.5,"lat":49.75},{"deg360":2.7,"lon":-116.95,"deg60":2.4,"deg90":2.4,"deg45":2.3,"deg0":1,"deg30":2,"lat":51.3},{"deg360":2.2,"lon":-118.45,"deg60":1.9,"deg90":1.9,"deg45":1.8,"deg0":1.1,"deg30":1.7,"lat":49.03},{"deg360":2.2,"lon":-126.22,"deg60":2,"deg90":2,"deg45":1.9,"deg0":0.6,"deg30":1.7,"lat":54.88},{"deg360":3.4,"lon":-115.08,"deg60":3,"deg90":2.9,"deg45":2.8,"deg0":1.3,"deg30":2.5,"lat":49.1},{"deg360":2.1,"lon":-118.68,"deg60":1.9,"deg90":1.8,"deg45":1.8,"deg0":1.1,"deg30":1.6,"lat":49.09},{"deg360":2.3,"lon":-119.12,"deg60":2,"deg90":2,"deg45":1.9,"deg0":1,"deg30":1.7,"lat":50.63},{"deg360":1.9,"lon":-126.55,"deg60":1.7,"deg90":1.6,"deg45":1.6,"deg0":0.6,"deg30":1.4,"lat":52.38},{"deg360":2,"lon":-121.78,"deg60":1.8,"deg90":1.7,"deg45":1.8,"deg0":0.9,"deg30":1.6,"lat":49.3},{"deg360":2,"lon":-121.95,"deg60":1.8,"deg90":1.8,"deg45":1.8,"deg0":0.9,"deg30":1.6,"lat":49.25},{"deg360":2.9,"lon":-116.45,"deg60":2.6,"deg90":2.5,"deg45":2.4,"deg0":1.1,"deg30":2.1,"lat":50.99},{"deg360":2.1,"lon":-122.24,"deg60":1.9,"deg90":1.8,"deg45":1.8,"deg0":0.9,"deg30":1.6,"lat":49.15},{"deg360":2.1,"lon":-127.68,"deg60":1.9,"deg90":1.9,"deg45":1.8,"deg0":0.6,"deg30":1.6,"lat":55.25},{"deg360":2.1,"lon":-120.07,"deg60":1.9,"deg90":1.8,"deg45":1.8,"deg0":1.1,"deg30":1.6,"lat":49.35},{"deg360":2,"lon":-125.19,"deg60":1.8,"deg90":1.7,"deg45":1.7,"deg0":0.8,"deg30":1.5,"lat":50.09},{"deg360":2.1,"lon":0,"deg60":1.9,"deg90":1.8,"deg45":1.8,"deg0":0.9,"deg30":1.6,"lat":-123.5},{"deg360":2.4,"lon":-122.58,"deg60":2.2,"deg90":2.1,"deg45":2.1,"deg0":0.7,"deg30":1.8,"lat":53.42},{"deg360":2,"lon":-124.17,"deg60":1.8,"deg90":1.7,"deg45":1.7,"deg0":0.8,"deg30":1.5,"lat":48.82},{"deg360":2,"lon":-121.44,"deg60":1.8,"deg90":1.7,"deg45":1.7,"deg0":0.9,"deg30":1.5,"lat":49.38},{"deg360":2,"lon":-124.68,"deg60":1.8,"deg90":1.7,"deg45":1.7,"deg0":0.8,"deg30":1.5,"lat":49.5},{"deg360":2.7,"lon":-121.41,"deg60":2.4,"deg90":2.4,"deg45":2.3,"deg0":0.8,"deg30":2,"lat":52.33},{"deg360":3.4,"lon":-114.96,"deg60":3,"deg90":2.9,"deg45":2.8,"deg0":1.2,"deg30":2.5,"lat":49.59},{"deg360":2.2,"lon":-126.65,"deg60":2,"deg90":1.9,"deg45":1.9,"deg0":0.6,"deg30":1.7,"lat":54.4},{"deg360":2.7,"lon":-121.9,"deg60":2.5,"deg90":2.5,"deg45":2.4,"deg0":0.7,"deg30":2.1,"lat":56.03},{"deg360":2.1,"lon":-122.26,"deg60":1.9,"deg90":1.8,"deg45":1.8,"deg0":0.9,"deg30":1.6,"lat":49},{"deg360":3.1,"lon":-116.03,"deg60":2.7,"deg90":2.7,"deg45":2.6,"deg0":1.1,"deg30":2.3,"lat":50.52},{"deg360":3.3,"lon":-115.3,"deg60":2.9,"deg90":2.9,"deg45":2.8,"deg0":1.2,"deg30":2.4,"lat":49.38},{"deg360":2.1,"lon":-119.61,"deg60":1.9,"deg90":1.8,"deg45":1.8,"deg0":1.1,"deg30":1.6,"lat":49.38},{"deg360":2.4,"lon":-120.35,"deg60":2.2,"deg90":2.1,"deg45":2.1,"deg0":1,"deg30":1.9,"lat":50.68},{"deg360":2.6,"lon":-116.91,"deg60":2.3,"deg90":2.2,"deg45":2.2,"deg0":1.1,"deg30":1.9,"lat":49.91},{"deg360":3,"lon":-120.02,"deg60":2.7,"deg90":2.7,"deg45":2.6,"deg0":0.7,"deg30":2.2,"lat":55.26},{"deg360":2.1,"lon":-119.45,"deg60":1.9,"deg90":1.8,"deg45":1.8,"deg0":1.1,"deg30":1.6,"lat":49.88},{"deg360":1.8,"lon":-127.94,"deg60":1.6,"deg90":1.6,"deg45":1.5,"deg0":0.6,"deg30":1.4,"lat":53.57},{"deg360":2,"lon":-121.72,"deg60":1.8,"deg90":1.7,"deg45":1.7,"deg0":0.9,"deg30":1.6,"lat":49.3},{"deg360":2.1,"lon":-119.83,"deg60":1.9,"deg90":1.8,"deg45":1.8,"deg0":1.1,"deg30":1.6,"lat":49.21},{"deg360":2.5,"lon":-122.42,"deg60":2.3,"deg90":2.2,"deg45":2.2,"deg0":0.8,"deg30":1.9,"lat":52.82},{"deg360":3,"lon":-115.96,"deg60":2.7,"deg90":2.6,"deg45":2.5,"deg0":1.2,"deg30":2.2,"lat":49.69},{"deg360":2.2,"lon":-118.73,"deg60":2,"deg90":2,"deg45":1.9,"deg0":1,"deg30":1.7,"lat":50.62},{"deg360":2.9,"lon":-116.18,"deg60":2.6,"deg90":2.5,"deg45":2.4,"deg0":1.2,"deg30":2.1,"lat":49},{"deg360":2.1,"lon":-127.7,"deg60":1.9,"deg90":1.9,"deg45":1.8,"deg0":0.6,"deg30":1.6,"lat":55.35},{"deg360":1.7,"lon":-128.64,"deg60":1.6,"deg90":1.5,"deg45":1.5,"deg0":0.5,"deg30":1.3,"lat":53.98},{"deg360":2.8,"lon":-116.34,"deg60":2.5,"deg90":2.4,"deg45":2.4,"deg0":1.2,"deg30":2.1,"lat":49.16},{"deg360":1.8,"lon":-128.61,"deg60":1.6,"deg90":1.6,"deg45":1.5,"deg0":0.5,"deg30":1.3,"lat":54.06},{"deg360":2,"lon":-127.82,"deg60":1.9,"deg90":1.8,"deg45":1.8,"deg0":0.6,"deg30":1.6,"lat":55.08},{"deg360":2,"lon":-128.07,"deg60":1.8,"deg90":1.8,"deg45":1.7,"deg0":0.6,"deg30":1.5,"lat":55.1},{"deg360":2.3,"lon":-117.58,"deg60":2.1,"deg90":2,"deg45":2,"deg0":1.1,"deg30":1.8,"lat":49.45},{"deg360":2.7,"lon":-121.47,"deg60":2.5,"deg90":2.4,"deg45":2.3,"deg0":0.9,"deg30":2.1,"lat":51.82},{"deg360":2.1,"lon":-123.08,"deg60":1.9,"deg90":1.8,"deg45":1.8,"deg0":0.9,"deg30":1.6,"lat":49.08},{"deg360":2.1,"lon":-123.82,"deg60":1.8,"deg90":1.7,"deg45":1.8,"deg0":0.9,"deg30":1.6,"lat":48.99},{"deg360":2,"lon":-121.61,"deg60":1.8,"deg90":1.7,"deg45":1.7,"deg0":0.9,"deg30":1.6,"lat":49.33},{"deg360":2.2,"lon":0,"deg60":2,"deg90":1.9,"deg45":1.9,"deg0":1.1,"deg30":1.7,"lat":-119.43},{"deg360":2,"lon":-124.06,"deg60":1.8,"deg90":1.7,"deg45":1.7,"deg0":0.9,"deg30":1.5,"lat":48.83},{"deg360":2,"lon":-122.02,"deg60":1.8,"deg90":1.8,"deg45":1.8,"deg0":0.9,"deg30":1.6,"lat":49.22},{"deg360":1.8,"lon":-128.53,"deg60":1.6,"deg90":1.6,"deg45":1.5,"deg0":0.5,"deg30":1.4,"lat":54.37},{"deg360":2.1,"lon":-119.53,"deg60":1.9,"deg90":1.8,"deg45":1.8,"deg0":1.1,"deg30":1.6,"lat":49.87},{"deg360":2,"lon":-124.35,"deg60":1.8,"deg90":1.7,"deg45":1.7,"deg0":0.8,"deg30":1.6,"lat":49.78},{"deg360":2.1,"lon":-123.5,"deg60":1.9,"deg90":1.8,"deg45":1.8,"deg0":0.9,"deg30":1.6,"lat":48.45},{"deg360":2.1,"lon":-122.54,"deg60":1.9,"deg90":1.8,"deg45":1.8,"deg0":0.9,"deg30":1.6,"lat":49.09},{"deg360":2.1,"lon":-124.04,"deg60":1.9,"deg90":1.8,"deg45":1.8,"deg0":0.9,"deg30":1.6,"lat":49.23},{"deg360":1.7,"lon":-130.43,"deg60":1.5,"deg90":1.5,"deg45":1.4,"deg0":0.5,"deg30":1.3,"lat":54.62},{"deg360":1.7,"lon":-129.58,"deg60":1.6,"deg90":1.6,"deg45":1.5,"deg0":0.5,"deg30":1.3,"lat":55.03},{"deg360":2,"lon":-124.93,"deg60":1.8,"deg90":1.7,"deg45":1.7,"deg0":0.8,"deg30":1.5,"lat":49.72},{"deg360":2.6,"lon":-121.55,"deg60":2.4,"deg90":2.4,"deg45":2.3,"deg0":0.8,"deg30":2,"lat":52.61},{"deg360":2.5,"lon":-121.93,"deg60":2.3,"deg90":2.2,"deg45":2.1,"deg0":0.9,"deg30":1.9,"lat":50.68},{"deg360":2,"lon":-123.23,"deg60":1.8,"deg90":1.7,"deg45":1.7,"deg0":0.8,"deg30":1.5,"lat":49.46},{"deg360":2.5,"lon":-120.21,"deg60":2.3,"deg90":2.3,"deg45":2.2,"deg0":1,"deg30":1.9,"lat":51.43},{"deg360":2.4,"lon":-120.83,"deg60":2.2,"deg90":2.1,"deg45":2.1,"deg0":1,"deg30":1.9,"lat":50.49},{"deg360":2.6,"lon":-121.16,"deg60":2.4,"deg90":2.3,"deg45":2.3,"deg0":0.9,"deg30":2,"lat":51.55},{"deg360":1.6,"lon":-128.5,"deg60":1.5,"deg90":1.5,"deg45":1.4,"deg0":0.4,"deg30":1.2,"lat":59.93},{"deg360":2.2,"lon":-118.96,"deg60":2,"deg90":1.9,"deg45":1.9,"deg0":1.1,"deg30":1.7,"lat":50.25},{"deg360":2,"lon":-124.74,"deg60":1.8,"deg90":1.7,"deg45":1.7,"deg0":0.8,"deg30":1.6,"lat":49.97},{"deg360":2.3,"lon":-121.57,"deg60":2.1,"deg90":2,"deg45":2,"deg0":0.9,"deg30":1.8,"lat":50.23},{"deg360":2.4,"lon":-123.1,"deg60":2.2,"deg90":2.1,"deg45":2,"deg0":0.6,"deg30":1.8,"lat":55.32},{"deg360":2.3,"lon":-118.78,"deg60":2,"deg90":2,"deg45":2,"deg0":1,"deg30":1.7,"lat":50.94},{"deg360":2,"lon":-124.99,"deg60":1.8,"deg90":1.7,"deg45":1.7,"deg0":0.8,"deg30":1.5,"lat":50.05},{"deg360":2.1,"lon":-122.59,"deg60":1.9,"deg90":1.8,"deg45":1.8,"deg0":0.9,"deg30":1.6,"lat":49.22},{"deg360":2.3,"lon":-119.05,"deg60":2,"deg90":2,"deg45":1.9,"deg0":1,"deg30":1.7,"lat":50.68},{"deg360":2.1,"lon":-126.06,"deg60":1.9,"deg90":1.8,"deg45":1.8,"deg0":0.8,"deg30":1.6,"lat":49.28},{"deg360":1.6,"lon":-132.13,"deg60":1.4,"deg90":1.4,"deg45":1.4,"deg0":0.6,"deg30":1.2,"lat":54.02},{"deg360":2.2,"lon":-123.3,"deg60":1.9,"deg90":1.8,"deg45":1.8,"deg0":0.9,"deg30":1.6,"lat":48.85},{"deg360":2.7,"lon":-120.19,"deg60":2.5,"deg90":2.5,"deg45":2.4,"deg0":0.8,"deg30":2.1,"lat":53.32},{"deg360":2.4,"lon":-123.03,"deg60":2.1,"deg90":2.1,"deg45":2,"deg0":0.6,"deg30":1.8,"lat":54.98},{"deg360":2.5,"lon":-120.23,"deg60":2.3,"deg90":2.2,"deg45":2.1,"deg0":1,"deg30":1.9,"lat":51.05},{"deg360":2.6,"lon":-116.98,"deg60":2.3,"deg90":2.2,"deg45":2.2,"deg0":1.1,"deg30":1.9,"lat":50.23},{"deg360":2.3,"lon":-120.79,"deg60":2.1,"deg90":2,"deg45":2,"deg0":1,"deg30":1.8,"lat":50.11},{"deg360":2,"lon":-125.07,"deg60":1.8,"deg90":1.7,"deg45":1.7,"deg0":0.8,"deg30":1.5,"lat":49.79},{"deg360":2.1,"lon":-118.77,"deg60":1.9,"deg90":1.8,"deg45":1.8,"deg0":1.1,"deg30":1.6,"lat":49.01},{"deg360":2.1,"lon":-123.56,"deg60":1.9,"deg90":1.8,"deg45":1.8,"deg0":0.9,"deg30":1.6,"lat":48.65},{"deg360":2.1,"lon":-122.3,"deg60":1.9,"deg90":1.8,"deg45":1.8,"deg0":0.9,"deg30":1.6,"lat":49.14},{"deg360":2.8,"lon":-121.73,"deg60":2.5,"deg90":2.5,"deg45":2.4,"deg0":0.7,"deg30":2.1,"lat":55.83},{"deg360":2.4,"lon":-119.95,"deg60":2.1,"deg90":2.1,"deg45":2,"deg0":1,"deg30":1.8,"lat":50.65},{"deg360":2.3,"lon":-119.84,"deg60":2.1,"deg90":2,"deg45":2,"deg0":1,"deg30":1.8,"lat":50.53},{"deg360":2.3,"lon":-117.6,"deg60":2.1,"deg90":2,"deg45":2,"deg0":1.1,"deg30":1.8,"lat":49.08},{"deg360":3,"lon":-115.81,"deg60":2.7,"deg90":2.6,"deg45":2.5,"deg0":1.2,"deg30":2.2,"lat":49.3},{"deg360":2.3,"lon":-117.8,"deg60":2.1,"deg90":2,"deg45":2,"deg0":1,"deg30":1.8,"lat":50.24},{"deg360":2.1,"lon":-123.94,"deg60":1.9,"deg90":1.8,"deg45":1.8,"deg0":0.9,"deg30":1.6,"lat":49.17},{"deg360":2.1,"lon":-124.21,"deg60":1.9,"deg90":1.8,"deg45":1.8,"deg0":0.9,"deg30":1.6,"lat":49.26},{"deg360":2.1,"lon":-119.58,"deg60":1.9,"deg90":1.8,"deg45":1.8,"deg0":1.1,"deg30":1.6,"lat":49.6},{"deg360":2.4,"lon":-117.29,"deg60":2.1,"deg90":2.1,"deg45":2,"deg0":1.1,"deg30":1.8,"lat":49.49},{"deg360":2.4,"lon":-117.29,"deg60":2.1,"deg90":2.1,"deg45":2,"deg0":1.1,"deg30":1.8,"lat":49},{"deg360":1.8,"lon":-129.08,"deg60":1.7,"deg90":1.6,"deg45":1.6,"deg0":0.5,"deg30":1.4,"lat":55.2},{"deg360":2.4,"lon":-117.36,"deg60":2.1,"deg90":2.1,"deg45":2,"deg0":1.1,"deg30":1.8,"lat":50},{"deg360":2.1,"lon":-127.58,"deg60":1.9,"deg90":1.9,"deg45":1.8,"deg0":0.6,"deg30":1.6,"lat":55.25},{"deg360":2.1,"lon":-122.9,"deg60":1.8,"deg90":1.8,"deg45":1.8,"deg0":0.9,"deg30":1.6,"lat":49.21},{"deg360":2.2,"lon":-121.45,"deg60":2,"deg90":1.9,"deg45":1.9,"deg0":0.9,"deg30":1.7,"lat":49.88},{"deg360":2.1,"lon":-123.66,"deg60":1.8,"deg90":1.7,"deg45":1.8,"deg0":0.9,"deg30":1.6,"lat":48.84},{"deg360":2.2,"lon":-123.42,"deg60":1.9,"deg90":1.8,"deg45":1.8,"deg0":0.9,"deg30":1.6,"lat":48.63},{"deg360":2,"lon":-123.06,"deg60":1.8,"deg90":1.7,"deg45":1.7,"deg0":0.8,"deg30":1.5,"lat":49.33},{"deg360":2.2,"lon":-123.3,"deg60":2,"deg90":1.9,"deg45":1.9,"deg0":1,"deg30":1.7,"lat":48.44},{"deg360":2.1,"lon":-119.58,"deg60":1.9,"deg90":1.8,"deg45":1.8,"deg0":1.1,"deg30":1.6,"lat":49.34},{"deg360":2.1,"lon":-119.84,"deg60":1.8,"deg90":1.8,"deg45":1.8,"deg0":1.1,"deg30":1.6,"lat":49.27},{"deg360":2.4,"lon":-122.5,"deg60":2.2,"deg90":2.2,"deg45":2,"deg0":0.5,"deg30":1.8,"lat":58.85},{"deg360":2.1,"lon":-119.55,"deg60":1.9,"deg90":1.8,"deg45":1.8,"deg0":1.1,"deg30":1.6,"lat":49.18},{"deg360":2.3,"lon":-117.63,"deg60":2.1,"deg90":2,"deg45":2,"deg0":1.1,"deg30":1.8,"lat":49.28},{"deg360":2.2,"lon":-126.05,"deg60":2,"deg90":1.9,"deg45":1.9,"deg0":0.7,"deg30":1.7,"lat":53.8},{"deg360":2.1,"lon":-125.91,"deg60":1.9,"deg90":1.8,"deg45":1.8,"deg0":0.8,"deg30":1.6,"lat":49.17},{"deg360":2.1,"lon":-119.48,"deg60":1.9,"deg90":1.8,"deg45":1.8,"deg0":1.1,"deg30":1.6,"lat":49.04},{"deg360":2.2,"lon":-119.37,"deg60":2,"deg90":1.9,"deg45":1.9,"deg0":1.1,"deg30":1.7,"lat":50.1},{"deg360":2.1,"lon":-124.32,"deg60":1.9,"deg90":1.8,"deg45":1.8,"deg0":0.9,"deg30":1.6,"lat":49.32},{"deg360":2.8,"lon":-116.63,"deg60":2.5,"deg90":2.4,"deg45":2.4,"deg0":1.1,"deg30":2.1,"lat":51.07},{"deg360":2.1,"lon":-119.74,"deg60":1.9,"deg90":1.8,"deg45":1.8,"deg0":1.1,"deg30":1.6,"lat":49.77},{"deg360":2.2,"lon":-122.8,"deg60":1.9,"deg90":1.9,"deg45":1.9,"deg0":0.8,"deg30":1.7,"lat":50.31},{"deg360":2.2,"lon":-123.28,"deg60":1.9,"deg90":1.8,"deg45":1.8,"deg0":0.9,"deg30":1.7,"lat":48.78},{"deg360":2.2,"lon":-125.72,"deg60":2,"deg90":2,"deg45":1.9,"deg0":0.7,"deg30":1.7,"lat":54.52},{"deg360":2.6,"lon":-121.29,"deg60":2.4,"deg90":2.4,"deg45":2.3,"deg0":0.7,"deg30":2,"lat":53.84},{"deg360":2.1,"lon":-119.59,"deg60":1.9,"deg90":1.8,"deg45":1.8,"deg0":1.1,"deg30":1.6,"lat":49.49},{"deg360":2.6,"lon":-122.51,"deg60":2.4,"deg90":2.4,"deg45":2.2,"deg0":0.6,"deg30":2,"lat":57.04},{"deg360":2.1,"lon":-122.69,"deg60":1.8,"deg90":1.8,"deg45":1.8,"deg0":0.9,"deg30":1.6,"lat":49.22},{"deg360":2,"lon":-121.73,"deg60":1.8,"deg90":1.7,"deg45":1.8,"deg0":0.9,"deg30":1.6,"lat":49.2},{"deg360":2,"lon":-124.81,"deg60":1.8,"deg90":1.7,"deg45":1.7,"deg0":0.8,"deg30":1.5,"lat":49.25},{"deg360":1.8,"lon":-127.45,"deg60":1.7,"deg90":1.6,"deg45":1.6,"deg0":0.7,"deg30":1.4,"lat":50.38},{"deg360":1.5,"lon":-132.16,"deg60":1.4,"deg90":1.3,"deg45":1.3,"deg0":0.6,"deg30":1.2,"lat":53.68},{"deg360":2,"lon":-122.76,"deg60":1.8,"deg90":1.7,"deg45":1.8,"deg0":0.9,"deg30":1.6,"lat":49.26},{"deg360":1.6,"lon":-130.28,"deg60":1.5,"deg90":1.5,"deg45":1.4,"deg0":0.5,"deg30":1.3,"lat":54.22},{"deg360":1.8,"lon":-127.49,"deg60":1.6,"deg90":1.5,"deg45":1.6,"deg0":0.7,"deg30":1.4,"lat":50.7},{"deg360":1.9,"lon":-127.1,"deg60":1.7,"deg90":1.6,"deg45":1.6,"deg0":0.7,"deg30":1.5,"lat":50.57},{"deg360":2,"lon":-123.49,"deg60":1.8,"deg90":1.7,"deg45":1.7,"deg0":0.8,"deg30":1.5,"lat":49.52},{"deg360":2,"lon":-122.85,"deg60":1.8,"deg90":1.7,"deg45":1.7,"deg0":0.9,"deg30":1.6,"lat":49.28},{"deg360":2.1,"lon":-124.42,"deg60":1.8,"deg90":1.7,"deg45":1.8,"deg0":0.9,"deg30":1.6,"lat":48.55},{"deg360":3,"lon":-120.13,"deg60":2.8,"deg90":2.8,"deg45":2.6,"deg0":0.7,"deg30":2.3,"lat":55.72},{"deg360":2.1,"lon":-124.53,"deg60":1.8,"deg90":1.7,"deg45":1.7,"deg0":0.8,"deg30":1.6,"lat":49.85},{"deg360":2.9,"lon":-121.05,"deg60":2.7,"deg90":2.7,"deg45":2.5,"deg0":0.6,"deg30":2.2,"lat":56.93},{"deg360":2.4,"lon":-122.74,"deg60":2.1,"deg90":2.1,"deg45":2,"deg0":0.7,"deg30":1.8,"lat":53.92},{"deg360":1.6,"lon":-130.32,"deg60":1.5,"deg90":1.5,"deg45":1.4,"deg0":0.5,"deg30":1.3,"lat":54.31},{"deg360":2.1,"lon":-120.51,"deg60":1.9,"deg90":1.8,"deg45":1.8,"deg0":1,"deg30":1.6,"lat":49.46},{"deg360":2.4,"lon":-119.82,"deg60":2.1,"deg90":2.1,"deg45":2,"deg0":1,"deg30":1.8,"lat":50.68},{"deg360":2.1,"lon":-124.44,"deg60":1.8,"deg90":1.7,"deg45":1.8,"deg0":0.9,"deg30":1.6,"lat":49.35},{"deg360":1.8,"lon":-127.65,"deg60":1.6,"deg90":1.5,"deg45":1.6,"deg0":0.7,"deg30":1.4,"lat":50.54},{"deg360":1.4,"lon":-132.04,"deg60":1.3,"deg90":1.2,"deg45":1.3,"deg0":0.6,"deg30":1.1,"lat":53.25},{"deg360":2.5,"lon":-122.51,"deg60":2.2,"deg90":2.2,"deg45":2.1,"deg0":0.8,"deg30":1.9,"lat":52.99},{"deg360":2.3,"lon":-120.5,"deg60":2.1,"deg90":2,"deg45":2,"deg0":1,"deg30":1.8,"lat":50.16},{"deg360":3.1,"lon":-116.07,"deg60":2.7,"deg90":2.7,"deg45":2.6,"deg0":1.1,"deg30":2.3,"lat":50.62},{"deg360":2.4,"lon":-122.67,"deg60":2.1,"deg90":2.1,"deg45":2,"deg0":0.7,"deg30":1.8,"lat":53.69},{"deg360":2.3,"lon":-118.21,"deg60":2.1,"deg90":2,"deg45":2,"deg0":1,"deg30":1.8,"lat":51.02},{"deg360":2.1,"lon":-119.02,"deg60":1.9,"deg90":1.8,"deg45":1.8,"deg0":1.1,"deg30":1.6,"lat":49.23},{"deg360":2.1,"lon":-123.11,"deg60":1.9,"deg90":1.8,"deg45":1.8,"deg0":0.9,"deg30":1.6,"lat":49.17},{"deg360":2.6,"lon":-116.85,"deg60":2.3,"deg90":2.2,"deg45":2.2,"deg0":1.1,"deg30":1.9,"lat":49.77},{"deg360":2,"lon":-123.64,"deg60":1.8,"deg90":1.7,"deg45":1.7,"deg0":0.8,"deg30":1.5,"lat":49.43},{"deg360":3,"lon":-120.13,"deg60":2.8,"deg90":2.8,"deg45":2.6,"deg0":0.7,"deg30":2.3,"lat":55.9},{"deg360":3.4,"lon":-115.05,"deg60":3,"deg90":2.9,"deg45":2.8,"deg0":1.3,"deg30":2.5,"lat":49},{"deg360":2.2,"lon":-117.81,"deg60":2,"deg90":1.9,"deg45":1.9,"deg0":1.1,"deg30":1.7,"lat":49.08},{"deg360":2,"lon":-124.96,"deg60":1.8,"deg90":1.7,"deg45":1.7,"deg0":0.8,"deg30":1.5,"lat":49.65},{"deg360":2.2,"lon":-123.39,"deg60":1.9,"deg90":1.8,"deg45":1.8,"deg0":0.9,"deg30":1.6,"lat":48.54},{"deg360":2.3,"lon":-119.27,"deg60":2,"deg90":2,"deg45":1.9,"deg0":1,"deg30":1.7,"lat":50.7},{"deg360":2.4,"lon":-117.27,"deg60":2.2,"deg90":2.1,"deg45":2.1,"deg0":1.1,"deg30":1.8,"lat":49.19},{"deg360":2.1,"lon":-123.77,"deg60":1.8,"deg90":1.7,"deg45":1.8,"deg0":0.9,"deg30":1.6,"lat":48.96},{"deg360":2,"lon":-124.13,"deg60":1.8,"deg90":1.7,"deg45":1.7,"deg0":0.8,"deg30":1.5,"lat":49.78},{"deg360":1.5,"lon":-131.81,"deg60":1.3,"deg90":1.3,"deg45":1.3,"deg0":0.6,"deg30":1.2,"lat":53.25},{"deg360":2.2,"lon":-123.17,"deg60":1.9,"deg90":1.8,"deg45":1.8,"deg0":0.9,"deg30":1.7,"lat":48.8},{"deg360":2.5,"lon":-120.83,"deg60":2.3,"deg90":2.2,"deg45":2.2,"deg0":1,"deg30":1.9,"lat":50.75},{"deg360":1.9,"lon":-125.95,"deg60":1.7,"deg90":1.7,"deg45":1.7,"deg0":0.7,"deg30":1.5,"lat":50.38},{"deg360":2.3,"lon":-119.45,"deg60":2.1,"deg90":2,"deg45":2,"deg0":1,"deg30":1.8,"lat":50.9},{"deg360":2,"lon":-123.77,"deg60":1.8,"deg90":1.7,"deg45":1.7,"deg0":0.9,"deg30":1.5,"lat":49.47},{"deg360":2.5,"lon":-122.21,"deg60":2.2,"deg90":2.2,"deg45":2.1,"deg0":0.9,"deg30":1.9,"lat":50.73},{"deg360":2.1,"lon":-123.63,"deg60":1.9,"deg90":1.8,"deg45":1.8,"deg0":0.9,"deg30":1.6,"lat":48.66},{"deg360":2.3,"lon":-120.84,"deg60":2.1,"deg90":2,"deg45":2,"deg0":1,"deg30":1.8,"lat":50.14},{"deg360":2.2,"lon":-118.82,"deg60":2,"deg90":1.9,"deg45":1.9,"deg0":1.1,"deg30":1.7,"lat":50.3},{"deg360":2.3,"lon":-118.98,"deg60":2,"deg90":2,"deg45":2,"deg0":1,"deg30":1.7,"lat":50.83},{"deg360":2.2,"lon":-123.42,"deg60":1.9,"deg90":1.8,"deg45":1.8,"deg0":0.9,"deg30":1.6,"lat":48.66},{"deg360":2.4,"lon":-117.35,"deg60":2.1,"deg90":2.1,"deg45":2,"deg0":1.1,"deg30":1.8,"lat":49.95},{"deg360":1.4,"lon":-131.99,"deg60":1.3,"deg90":1.3,"deg45":1.3,"deg0":0.6,"deg30":1.2,"lat":53.27},{"deg360":2,"lon":-121.82,"deg60":1.8,"deg90":1.8,"deg45":1.8,"deg0":0.9,"deg30":1.6,"lat":49.08},{"deg360":2.1,"lon":-124.57,"deg60":1.8,"deg90":1.7,"deg45":1.7,"deg0":0.8,"deg30":1.6,"lat":49.89},{"deg360":2.3,"lon":-117.46,"deg60":2.1,"deg90":2,"deg45":2,"deg0":1.1,"deg30":1.8,"lat":49.77},{"deg360":2.1,"lon":-127.17,"deg60":2,"deg90":1.9,"deg45":1.8,"deg0":0.6,"deg30":1.6,"lat":54.78},{"deg360":1.9,"lon":-127.04,"deg60":1.7,"deg90":1.6,"deg45":1.6,"deg0":0.7,"deg30":1.5,"lat":50.65},{"deg360":2.1,"lon":-123.72,"deg60":1.9,"deg90":1.8,"deg45":1.8,"deg0":0.9,"deg30":1.6,"lat":48.38},{"deg360":2.3,"lon":-119.47,"deg60":2.1,"deg90":2,"deg45":2,"deg0":1,"deg30":1.8,"lat":50.88},{"deg360":2.2,"lon":-125.77,"deg60":2,"deg90":1.9,"deg45":1.9,"deg0":0.7,"deg30":1.7,"lat":54.02},{"deg360":2.2,"lon":-119.23,"deg60":2,"deg90":1.9,"deg45":1.9,"deg0":1,"deg30":1.7,"lat":50.44},{"deg360":3.4,"lon":-114.89,"deg60":3.1,"deg90":3,"deg45":2.9,"deg0":1.2,"deg30":2.5,"lat":49.72},{"deg360":2.4,"lon":-121.35,"deg60":2.2,"deg90":2.1,"deg45":2.1,"deg0":1,"deg30":1.9,"lat":50.41},{"deg360":2.9,"lon":-116.35,"deg60":2.6,"deg90":2.5,"deg45":2.5,"deg0":1.1,"deg30":2.2,"lat":50.9},{"deg360":2,"lon":-124.93,"deg60":1.8,"deg90":1.7,"deg45":1.7,"deg0":0.8,"deg30":1.5,"lat":49.3},{"deg360":2,"lon":-123.13,"deg60":1.8,"deg90":1.7,"deg45":1.7,"deg0":0.8,"deg30":1.5,"lat":49.74},{"deg360":1.7,"lon":-130.01,"deg60":1.5,"deg90":1.5,"deg45":1.5,"deg0":0.5,"deg30":1.3,"lat":55.92},{"deg360":2.2,"lon":-123.32,"deg60":1.9,"deg90":1.8,"deg45":1.8,"deg0":0.9,"deg30":1.6,"lat":48.88},{"deg360":2.7,"lon":-121.99,"deg60":2.4,"deg90":2.4,"deg45":2.3,"deg0":0.9,"deg30":2,"lat":52.11},{"deg360":2.1,"lon":-119.66,"deg60":1.9,"deg90":1.8,"deg45":1.8,"deg0":1.1,"deg30":1.6,"lat":49.6},{"deg360":2.1,"lon":-122.84,"deg60":1.9,"deg90":1.8,"deg45":1.8,"deg0":0.9,"deg30":1.6,"lat":49.18},{"deg360":2.2,"lon":-124.68,"deg60":2,"deg90":2,"deg45":1.9,"deg0":0.7,"deg30":1.7,"lat":54.64},{"deg360":2.4,"lon":-117.39,"deg60":2.1,"deg90":2,"deg45":2,"deg0":1.1,"deg30":1.8,"lat":49.49},{"deg360":2,"lon":-126.67,"deg60":1.8,"deg90":1.7,"deg45":1.7,"deg0":0.8,"deg30":1.5,"lat":49.92},{"deg360":2.3,"lon":-119.33,"deg60":2,"deg90":2,"deg45":2,"deg0":1,"deg30":1.7,"lat":50.78},{"deg360":3,"lon":-120.68,"deg60":2.7,"deg90":2.7,"deg45":2.6,"deg0":0.7,"deg30":2.3,"lat":56.16},{"deg360":1.7,"lon":-131.17,"deg60":1.5,"deg90":1.5,"deg45":1.5,"deg0":0.5,"deg30":1.3,"lat":57.9},{"deg360":2.2,"lon":-127.05,"deg60":2,"deg90":1.9,"deg45":1.9,"deg0":0.6,"deg30":1.6,"lat":54.7},{"deg360":1.8,"lon":-128.62,"deg60":1.7,"deg90":1.6,"deg45":1.6,"deg0":0.5,"deg30":1.4,"lat":54.52},{"deg360":2.3,"lon":-117.6,"deg60":2.1,"deg90":2,"deg45":2,"deg0":1.1,"deg30":1.8,"lat":49.35},{"deg360":2.2,"lon":-125.59,"deg60":2,"deg90":2,"deg45":1.9,"deg0":0.7,"deg30":1.7,"lat":54.2},{"deg360":1.5,"lon":-131.94,"deg60":1.4,"deg90":1.3,"deg45":1.4,"deg0":0.6,"deg30":1.2,"lat":53.58},{"deg360":2.1,"lon":-125.9,"deg60":1.9,"deg90":1.8,"deg45":1.8,"deg0":0.8,"deg30":1.6,"lat":49.15},{"deg360":2.2,"lon":-126.3,"deg60":2,"deg90":2,"deg45":1.9,"deg0":0.7,"deg30":1.7,"lat":54.51},{"deg360":2.3,"lon":-117.72,"deg60":2.1,"deg90":2,"deg45":2,"deg0":1.1,"deg30":1.8,"lat":49.1},{"deg360":2.4,"lon":-122.95,"deg60":2.2,"deg90":2.2,"deg45":2.1,"deg0":0.6,"deg30":1.9,"lat":57.74},{"deg360":2.2,"lon":-123.09,"deg60":1.9,"deg90":1.8,"deg45":1.8,"deg0":0.9,"deg30":1.6,"lat":49.02},{"deg360":2.8,"lon":-120.99,"deg60":2.6,"deg90":2.6,"deg45":2.4,"deg0":0.7,"deg30":2.1,"lat":55.14},{"deg360":2.1,"lon":-125.55,"deg60":1.9,"deg90":1.8,"deg45":1.8,"deg0":0.8,"deg30":1.6,"lat":48.94},{"deg360":2,"lon":-124.89,"deg60":1.8,"deg90":1.7,"deg45":1.7,"deg0":0.8,"deg30":1.5,"lat":49.59},{"deg360":2.5,"lon":-121.94,"deg60":2.3,"deg90":2.2,"deg45":2.1,"deg0":0.7,"deg30":1.9,"lat":54.11},{"deg360":1.9,"lon":-128.42,"deg60":1.7,"deg90":1.7,"deg45":1.6,"deg0":0.6,"deg30":1.4,"lat":54.64},{"deg360":2.7,"lon":-119.26,"deg60":2.4,"deg90":2.4,"deg45":2.3,"deg0":0.9,"deg30":2,"lat":52.83},{"deg360":2.1,"lon":-124.55,"deg60":1.8,"deg90":1.7,"deg45":1.8,"deg0":0.8,"deg30":1.6,"lat":49.76},{"deg360":2.1,"lon":-123.11,"deg60":1.8,"deg90":1.8,"deg45":1.8,"deg0":0.9,"deg30":1.6,"lat":49.25},{"deg360":2.3,"lon":-124.01,"deg60":2.1,"deg90":2,"deg45":1.9,"deg0":0.7,"deg30":1.7,"lat":54.01},{"deg360":2.5,"lon":-119.72,"deg60":2.3,"deg90":2.2,"deg45":2.2,"deg0":0.9,"deg30":1.9,"lat":51.59},{"deg360":2.2,"lon":-119.27,"deg60":2,"deg90":1.9,"deg45":1.9,"deg0":1.1,"deg30":1.7,"lat":50.26},{"deg360":2.2,"lon":-123.37,"deg60":2,"deg90":1.8,"deg45":1.9,"deg0":0.9,"deg30":1.7,"lat":48.43},{"deg360":1.7,"lon":-128.14,"deg60":1.6,"deg90":1.5,"deg45":1.5,"deg0":0.6,"deg30":1.3,"lat":52.16},{"deg360":2.5,"lon":-120.97,"deg60":2.3,"deg90":2.2,"deg45":2.2,"deg0":1,"deg30":1.9,"lat":50.75},{"deg360":3.2,"lon":-115.75,"deg60":2.8,"deg90":2.7,"deg45":2.6,"deg0":1.2,"deg30":2.3,"lat":49.79},{"deg360":2.5,"lon":-121.58,"deg60":2.3,"deg90":2.3,"deg45":2.2,"deg0":0.8,"deg30":1.9,"lat":53.1},{"deg360":2,"lon":-123.17,"deg60":1.8,"deg90":1.7,"deg45":1.7,"deg0":0.8,"deg30":1.5,"lat":49.35},{"deg360":2.1,"lon":-119.63,"deg60":1.9,"deg90":1.8,"deg45":1.8,"deg0":1.1,"deg30":1.6,"lat":49.83},{"deg360":2.3,"lon":-119.75,"deg60":2.1,"deg90":2,"deg45":2,"deg0":1,"deg30":1.8,"lat":50.47},{"deg360":2.1,"lon":-122.99,"deg60":1.9,"deg90":1.8,"deg45":1.8,"deg0":0.8,"deg30":1.6,"lat":50.1},{"deg360":2.1,"lon":-122.8,"deg60":1.9,"deg90":1.8,"deg45":1.8,"deg0":0.9,"deg30":1.6,"lat":49.02},{"deg360":2.7,"lon":-122.13,"deg60":2.4,"deg90":2.4,"deg45":2.3,"deg0":0.9,"deg30":2,"lat":52.13},{"deg360":2.4,"lon":-122.46,"deg60":2.2,"deg90":2.1,"deg45":2,"deg0":0.7,"deg30":1.8,"lat":54.07},{"deg360":3.1,"lon":-115.97,"deg60":2.7,"deg90":2.7,"deg45":2.6,"deg0":1.1,"deg30":2.3,"lat":50.46},{"deg360":2.3,"lon":-117.55,"deg60":2.1,"deg90":2,"deg45":2,"deg0":1.1,"deg30":1.8,"lat":49.62},{"deg360":2.8,"lon":-121.68,"deg60":2.6,"deg90":2.6,"deg45":2.4,"deg0":0.6,"deg30":2.1,"lat":56.67},{"deg360":2.2,"lon":-119.39,"deg60":1.9,"deg90":1.9,"deg45":1.9,"deg0":1.1,"deg30":1.7,"lat":50.05},{"deg360":2.7,"lon":-116.57,"deg60":2.4,"deg90":2.3,"deg45":2.3,"deg0":1.2,"deg30":2,"lat":49.19},{"deg360":2.9,"lon":-116.09,"deg60":2.6,"deg90":2.5,"deg45":2.5,"deg0":1.2,"deg30":2.2,"lat":49.09},{"deg360":2,"lon":-121.44,"deg60":1.8,"deg90":1.7,"deg45":1.8,"deg0":0.9,"deg30":1.6,"lat":49.56},{"deg360":2,"lon":-122.04,"deg60":1.8,"deg90":1.8,"deg45":1.8,"deg0":0.9,"deg30":1.6,"lat":49.06},{"deg360":2.4,"lon":-117.21,"deg60":2.2,"deg90":2.1,"deg45":2.1,"deg0":1.1,"deg30":1.8,"lat":49.28},{"deg360":2,"lon":-124.17,"deg60":1.8,"deg90":1.7,"deg45":1.7,"deg0":0.8,"deg30":1.5,"lat":48.87},{"deg360":1.9,"lon":-126.85,"deg60":1.7,"deg90":1.7,"deg45":1.7,"deg0":0.8,"deg30":1.5,"lat":49.99}]